setup.py
mpqcv/My_CV.cp39-win_amd64.pyd
mpqcv/__init__.py
mpqcv.egg-info/PKG-INFO
mpqcv.egg-info/SOURCES.txt
mpqcv.egg-info/dependency_links.txt
mpqcv.egg-info/requires.txt
mpqcv.egg-info/top_level.txt