Metadata-Version: 2.1
Name: mpqcv
Version: 0.0.16
Summary: CV for MPQ
Home-page: https://github.com/miaopeiqi
Author: MPQ
Author-email: miaopeiqi@163.com
License: UNKNOWN
Platform: UNKNOWN
